MANIFEST.in
README.md
requirements.txt
setup.py
keras_adabound/__init__.py
keras_adabound/backend.py
keras_adabound/optimizers.py
keras_adabound.egg-info/PKG-INFO
keras_adabound.egg-info/SOURCES.txt
keras_adabound.egg-info/dependency_links.txt
keras_adabound.egg-info/requires.txt
keras_adabound.egg-info/top_level.txt
tests/__init__.py
tests/test_optimize.py
tests/test_similar.py