Metadata-Version: 2.1
Name: keras-adabound
Version: 0.5.0
Summary: AdaBound optimizer in Keras
Home-page: https://github.com/CyberZHG/keras-adabound
Author: CyberZHG
Author-email: CyberZHG@gmail.com
License: MIT
Platform: UNKNOWN
Classifier: Programming Language :: Python :: 2.7
Classifier: Programming Language :: Python :: 3.6
Classifier: License :: OSI Approved :: MIT License
Classifier: Operating System :: OS Independent
